LICENSE
MANIFEST.in
README.rst
setup.py
mezzanine_polls/__init__.py
mezzanine_polls/admin.py
mezzanine_polls/forms.py
mezzanine_polls/models.py
mezzanine_polls/page_processors.py
mezzanine_polls/tests.py
mezzanine_polls/views.py
mezzanine_polls.egg-info/PKG-INFO
mezzanine_polls.egg-info/SOURCES.txt
mezzanine_polls.egg-info/dependency_links.txt
mezzanine_polls.egg-info/not-zip-safe
mezzanine_polls.egg-info/requires.txt
mezzanine_polls.egg-info/top_level.txt
mezzanine_polls/templates/pages/poll.html