Metadata-Version: 1.1
Name: mezzanine-polls
Version: 0.3.2
Summary: Polls application for the Mezzanine CMS
Home-page: https://bitbucket.org/sebasmagri/mezzanine_polls
Author: Sebastian Magri
Author-email: sebasmagri@gmail.com
License: BSD
Keywords: django,mezzanine,polls
Platform: UNKNOWN
Classifier: Development Status :: 3 - Alpha
Classifier: Environment :: Web Environment
Classifier: Framework :: Django
Classifier: Intended Audience :: Developers
Classifier: License :: OSI Approved :: BSD License
Classifier: Operating System :: OS Independent
Classifier: Programming Language :: Python
Classifier: Topic :: Internet :: WWW/HTTP
Classifier: Topic :: Internet :: WWW/HTTP :: Dynamic Content
Classifier: Topic :: Internet :: WWW/HTTP :: WSGI
Classifier: Topic :: Software Development :: Libraries :: Application Frameworks
Classifier: Topic :: Software Development :: Libraries :: Python Modules
